[
    {
        "sku": "ANM-11001",
        "keywords": " 1",
        "name": "MOD: ANM-11001",
        "hot": false,
        "new": false,
        "image": "https://i.ibb.co/LzXkGt9c/ANIME-01.png",
        "link": "https://api.whatsapp.com/send?phone=2411576300&text=Hola!%20Me%20interesa%20un%20Estampado%20con%20este%20Dise%C3%B1o%20%22ANM-11001%22"
    },
    {
        "sku": "ANM-11002",
        "keywords": " 2",
        "name": "MOD: ANM-11002",
        "hot": false,
        "new": false,
        "image": "https://i.ibb.co/Myd7TXz4/ANIME-02.png",
        "link": "https://api.whatsapp.com/send?phone=2411576300&text=Hola!%20Me%20interesa%20un%20Estampado%20con%20este%20Dise%C3%B1o%20%22ANM-11002%22"
    },
    {
        "sku": "ANM-11003",
        "keywords": " 3",
        "name": "MOD: ANM-11003",
        "hot": false,
        "new": false,
        "image": "https://i.ibb.co/RGWGb6ZJ/ANIME-03.png",
        "link": "https://api.whatsapp.com/send?phone=2411576300&text=Hola!%20Me%20interesa%20un%20Estampado%20con%20este%20Dise%C3%B1o%20%22ANM-11003%22"
    },
    {
        "sku": "ANM-11004",
        "keywords": " 4",
        "name": "MOD: ANM-11004",
        "hot": false,
        "new": false,
        "image": "https://i.ibb.co/GvT7QFkb/ANIME-04.png",
        "link": "https://api.whatsapp.com/send?phone=2411576300&text=Hola!%20Me%20interesa%20un%20Estampado%20con%20este%20Dise%C3%B1o%20%22ANM-11004%22"
    },
    {
        "sku": "ANM-11005",
        "keywords": " 5",
        "name": "MOD: ANM-11005",
        "hot": false,
        "new": false,
        "image": "https://i.ibb.co/q38kbsmJ/ANIME-05.png",
        "link": "https://api.whatsapp.com/send?phone=2411576300&text=Hola!%20Me%20interesa%20un%20Estampado%20con%20este%20Dise%C3%B1o%20%22ANM-11005%22"
    },
    {
        "sku": "ANM-11006",
        "keywords": " 6",
        "name": "MOD: ANM-11006",
        "hot": false,
        "new": false,
        "image": "https://i.ibb.co/v4S9QWrX/ANIME-06.png",
        "link": "https://api.whatsapp.com/send?phone=2411576300&text=Hola!%20Me%20interesa%20un%20Estampado%20con%20este%20Dise%C3%B1o%20%22ANM-11006%22"
    },
    {
        "sku": "ANM-11007",
        "keywords": " 7",
        "name": "MOD: ANM-11007",
        "hot": false,
        "new": false,
        "image": "https://i.ibb.co/pGq4PVm/ANIME-07.png",
        "link": "https://api.whatsapp.com/send?phone=2411576300&text=Hola!%20Me%20interesa%20un%20Estampado%20con%20este%20Dise%C3%B1o%20%22ANM-11007%22"
    },
    {
        "sku": "ANM-11008",
        "keywords": " 8",
        "name": "MOD: ANM-11008",
        "hot": false,
        "new": false,
        "image": "https://i.ibb.co/GXX3PKQ/ANIME-08.png",
        "link": "https://api.whatsapp.com/send?phone=2411576300&text=Hola!%20Me%20interesa%20un%20Estampado%20con%20este%20Dise%C3%B1o%20%22ANM-11008%22"
    },
    {
        "sku": "ANM-11009",
        "keywords": " 9",
        "name": "MOD: ANM-11009",
        "hot": false,
        "new": false,
        "image": "https://i.ibb.co/bYFFWr1/ANIME-09.png",
        "link": "https://api.whatsapp.com/send?phone=2411576300&text=Hola!%20Me%20interesa%20un%20Estampado%20con%20este%20Dise%C3%B1o%20%22ANM-11009%22"
    },
    {
        "sku": "ANM-11010",
        "keywords": " 10",
        "name": "MOD: ANM-11010",
        "hot": false,
        "new": false,
        "image": "https://i.ibb.co/dJchTt9M/ANIME-10.png",
        "link": "https://api.whatsapp.com/send?phone=2411576300&text=Hola!%20Me%20interesa%20un%20Estampado%20con%20este%20Dise%C3%B1o%20%22ANM-11010%22"
    },
    {
        "sku": "ANM-11011",
        "keywords": " 11",
        "name": "MOD: ANM-11011",
        "hot": false,
        "new": false,
        "image": "https://i.ibb.co/FqcDynJH/ANIME-11.png",
        "link": "https://api.whatsapp.com/send?phone=2411576300&text=Hola!%20Me%20interesa%20un%20Estampado%20con%20este%20Dise%C3%B1o%20%22ANM-11011%22"
    },
    {
        "sku": "ANM-11012",
        "keywords": " 12",
        "name": "MOD: ANM-11012",
        "hot": false,
        "new": false,
        "image": "https://i.ibb.co/JfQX8Vg/ANIME-12.png",
        "link": "https://api.whatsapp.com/send?phone=2411576300&text=Hola!%20Me%20interesa%20un%20Estampado%20con%20este%20Dise%C3%B1o%20%22ANM-11012%22"
    },
    {
        "sku": "ANM-11013",
        "keywords": " 13",
        "name": "MOD: ANM-11013",
        "hot": false,
        "new": false,
        "image": "https://i.ibb.co/WvYSF09q/ANIME-13.png",
        "link": "https://api.whatsapp.com/send?phone=2411576300&text=Hola!%20Me%20interesa%20un%20Estampado%20con%20este%20Dise%C3%B1o%20%22ANM-11013%22"
    },
    {
        "sku": "ANM-11014",
        "keywords": " 14",
        "name": "MOD: ANM-11014",
        "hot": false,
        "new": false,
        "image": "https://i.ibb.co/q3ftWdsM/ANIME-14.png",
        "link": "https://api.whatsapp.com/send?phone=2411576300&text=Hola!%20Me%20interesa%20un%20Estampado%20con%20este%20Dise%C3%B1o%20%22ANM-11014%22"
    },
    {
        "sku": "ANM-11015",
        "keywords": " 15",
        "name": "MOD: ANM-11015",
        "hot": false,
        "new": false,
        "image": "https://i.ibb.co/h1Xs2NjV/ANIME-15.png",
        "link": "https://api.whatsapp.com/send?phone=2411576300&text=Hola!%20Me%20interesa%20un%20Estampado%20con%20este%20Dise%C3%B1o%20%22ANM-11015%22"
    },
    {
        "sku": "ANM-11016",
        "keywords": " 16",
        "name": "MOD: ANM-11016",
        "hot": false,
        "new": false,
        "image": "https://i.ibb.co/rGyGn4zp/ANIME-16.png",
        "link": "https://api.whatsapp.com/send?phone=2411576300&text=Hola!%20Me%20interesa%20un%20Estampado%20con%20este%20Dise%C3%B1o%20%22ANM-11016%22"
    },
    {
        "sku": "ANM-11017",
        "keywords": " 17",
        "name": "MOD: ANM-11017",
        "hot": false,
        "new": false,
        "image": "https://i.ibb.co/qL7PqCmX/ANIME-17.png",
        "link": "https://api.whatsapp.com/send?phone=2411576300&text=Hola!%20Me%20interesa%20un%20Estampado%20con%20este%20Dise%C3%B1o%20%22ANM-11017%22"
    },
    {
        "sku": "ANM-11018",
        "keywords": " 18",
        "name": "MOD: ANM-11018",
        "hot": false,
        "new": false,
        "image": "https://i.ibb.co/v4rYv5HV/ANIME-18.png",
        "link": "https://api.whatsapp.com/send?phone=2411576300&text=Hola!%20Me%20interesa%20un%20Estampado%20con%20este%20Dise%C3%B1o%20%22ANM-11018%22"
    },
    {
        "sku": "ANM-11019",
        "keywords": " 19",
        "name": "MOD: ANM-11019",
        "hot": false,
        "new": false,
        "image": "https://i.ibb.co/GvbkWT47/ANIME-19.png",
        "link": "https://api.whatsapp.com/send?phone=2411576300&text=Hola!%20Me%20interesa%20un%20Estampado%20con%20este%20Dise%C3%B1o%20%22ANM-11019%22"
    },
    {
        "sku": "ANM-11020",
        "keywords": " 20",
        "name": "MOD: ANM-11020",
        "hot": false,
        "new": false,
        "image": "https://i.ibb.co/ds0fmhbL/ANIME-20.png",
        "link": "https://api.whatsapp.com/send?phone=2411576300&text=Hola!%20Me%20interesa%20un%20Estampado%20con%20este%20Dise%C3%B1o%20%22ANM-11020%22"
    },
    {
        "sku": "ANM-11021",
        "keywords": " 21",
        "name": "MOD: ANM-11021",
        "hot": false,
        "new": false,
        "image": "https://i.ibb.co/GQr8GYwD/ANIME-21.png",
        "link": "https://api.whatsapp.com/send?phone=2411576300&text=Hola!%20Me%20interesa%20un%20Estampado%20con%20este%20Dise%C3%B1o%20%22ANM-11021%22"
    },
    {
        "sku": "ANM-11022",
        "keywords": " 22",
        "name": "MOD: ANM-11022",
        "hot": false,
        "new": false,
        "image": "https://i.ibb.co/7J8w95jL/ANIME-22.png",
        "link": "https://api.whatsapp.com/send?phone=2411576300&text=Hola!%20Me%20interesa%20un%20Estampado%20con%20este%20Dise%C3%B1o%20%22ANM-11022%22"
    },
    {
        "sku": "ANM-11023",
        "keywords": " 23",
        "name": "MOD: ANM-11023",
        "hot": false,
        "new": false,
        "image": "https://i.ibb.co/JFpLRjyG/ANIME-23.png",
        "link": "https://api.whatsapp.com/send?phone=2411576300&text=Hola!%20Me%20interesa%20un%20Estampado%20con%20este%20Dise%C3%B1o%20%22ANM-11023%22"
    },
    {
        "sku": "ANM-11024",
        "keywords": " 24",
        "name": "MOD: ANM-11024",
        "hot": false,
        "new": false,
        "image": "https://i.ibb.co/rGYjcQMR/ANIME-24.png",
        "link": "https://api.whatsapp.com/send?phone=2411576300&text=Hola!%20Me%20interesa%20un%20Estampado%20con%20este%20Dise%C3%B1o%20%22ANM-11024%22"
    },
    {
        "sku": "ANM-11025",
        "keywords": " 25",
        "name": "MOD: ANM-11025",
        "hot": false,
        "new": false,
        "image": "https://i.ibb.co/RkYVzYNy/ANIME-25.png",
        "link": "https://api.whatsapp.com/send?phone=2411576300&text=Hola!%20Me%20interesa%20un%20Estampado%20con%20este%20Dise%C3%B1o%20%22ANM-11025%22"
    },
    {
        "sku": "ANM-11026",
        "keywords": " 26",
        "name": "MOD: ANM-11026",
        "hot": false,
        "new": false,
        "image": "https://i.ibb.co/gZvTNxTV/ANIME-26.png",
        "link": "https://api.whatsapp.com/send?phone=2411576300&text=Hola!%20Me%20interesa%20un%20Estampado%20con%20este%20Dise%C3%B1o%20%22ANM-11026%22"
    },
    {
        "sku": "ANM-11027",
        "keywords": " 27",
        "name": "MOD: ANM-11027",
        "hot": false,
        "new": false,
        "image": "https://i.ibb.co/bRLFgdrj/ANIME-27.png",
        "link": "https://api.whatsapp.com/send?phone=2411576300&text=Hola!%20Me%20interesa%20un%20Estampado%20con%20este%20Dise%C3%B1o%20%22ANM-11027%22"
    },
    {
        "sku": "ANM-11028",
        "keywords": " 28",
        "name": "MOD: ANM-11028",
        "hot": false,
        "new": false,
        "image": "https://i.ibb.co/bj4sXxGj/ANIME-28.png",
        "link": "https://api.whatsapp.com/send?phone=2411576300&text=Hola!%20Me%20interesa%20un%20Estampado%20con%20este%20Dise%C3%B1o%20%22ANM-11028%22"
    },
    {
        "sku": "ANM-11029",
        "keywords": " 29",
        "name": "MOD: ANM-11029",
        "hot": false,
        "new": false,
        "image": "https://i.ibb.co/Ldw6jqzw/ANIME-29.png",
        "link": "https://api.whatsapp.com/send?phone=2411576300&text=Hola!%20Me%20interesa%20un%20Estampado%20con%20este%20Dise%C3%B1o%20%22ANM-11029%22"
    },
    {
        "sku": "ANM-11030",
        "keywords": " 30",
        "name": "MOD: ANM-11030",
        "hot": false,
        "new": false,
        "image": "https://i.ibb.co/qLQ4rLfN/ANIME-30.png",
        "link": "https://api.whatsapp.com/send?phone=2411576300&text=Hola!%20Me%20interesa%20un%20Estampado%20con%20este%20Dise%C3%B1o%20%22ANM-11030%22"
    },
    {
        "sku": "ANM-11031",
        "keywords": " 31",
        "name": "MOD: ANM-11031",
        "hot": false,
        "new": false,
        "image": "https://i.ibb.co/M5cbtxg3/ANIME-31.png",
        "link": "https://api.whatsapp.com/send?phone=2411576300&text=Hola!%20Me%20interesa%20un%20Estampado%20con%20este%20Dise%C3%B1o%20%22ANM-11031%22"
    },
    {
        "sku": "ANM-11032",
        "keywords": " 32",
        "name": "MOD: ANM-11032",
        "hot": false,
        "new": false,
        "image": "https://i.ibb.co/4R15VDRW/ANIME-32.png",
        "link": "https://api.whatsapp.com/send?phone=2411576300&text=Hola!%20Me%20interesa%20un%20Estampado%20con%20este%20Dise%C3%B1o%20%22ANM-11032%22"
    },
    {
        "sku": "ANM-11033",
        "keywords": " 33",
        "name": "MOD: ANM-11033",
        "hot": false,
        "new": false,
        "image": "https://i.ibb.co/1JvY3WYN/ANIME-33.png",
        "link": "https://api.whatsapp.com/send?phone=2411576300&text=Hola!%20Me%20interesa%20un%20Estampado%20con%20este%20Dise%C3%B1o%20%22ANM-11033%22"
    },
    {
        "sku": "ANM-11034",
        "keywords": " 34",
        "name": "MOD: ANM-11034",
        "hot": false,
        "new": false,
        "image": "https://i.ibb.co/zV1YFn3k/ANIME-34.png",
        "link": "https://api.whatsapp.com/send?phone=2411576300&text=Hola!%20Me%20interesa%20un%20Estampado%20con%20este%20Dise%C3%B1o%20%22ANM-11034%22"
    },
    {
        "sku": "ANM-11035",
        "keywords": " 35",
        "name": "MOD: ANM-11035",
        "hot": false,
        "new": false,
        "image": "https://i.ibb.co/Mx07R3Qn/ANIME-35.png",
        "link": "https://api.whatsapp.com/send?phone=2411576300&text=Hola!%20Me%20interesa%20un%20Estampado%20con%20este%20Dise%C3%B1o%20%22ANM-11035%22"
    },
    {
        "sku": "ANM-11036",
        "keywords": " 36",
        "name": "MOD: ANM-11036",
        "hot": false,
        "new": false,
        "image": "https://i.ibb.co/G3tf8CRr/ANIME-36.png",
        "link": "https://api.whatsapp.com/send?phone=2411576300&text=Hola!%20Me%20interesa%20un%20Estampado%20con%20este%20Dise%C3%B1o%20%22ANM-11036%22"
    },
    {
        "sku": "ANM-11037",
        "keywords": " 37",
        "name": "MOD: ANM-11037",
        "hot": false,
        "new": false,
        "image": "https://i.ibb.co/cmtdNV4/ANIME-37.png",
        "link": "https://api.whatsapp.com/send?phone=2411576300&text=Hola!%20Me%20interesa%20un%20Estampado%20con%20este%20Dise%C3%B1o%20%22ANM-11037%22"
    },
    {
        "sku": "ANM-11038",
        "keywords": " 38",
        "name": "MOD: ANM-11038",
        "hot": false,
        "new": false,
        "image": "https://i.ibb.co/5XWRpYqq/ANIME-38.png",
        "link": "https://api.whatsapp.com/send?phone=2411576300&text=Hola!%20Me%20interesa%20un%20Estampado%20con%20este%20Dise%C3%B1o%20%22ANM-11038%22"
    },
    {
        "sku": "ANM-11039",
        "keywords": " 39",
        "name": "MOD: ANM-11039",
        "hot": false,
        "new": false,
        "image": "https://i.ibb.co/CpF71dFr/ANIME-39.png",
        "link": "https://api.whatsapp.com/send?phone=2411576300&text=Hola!%20Me%20interesa%20un%20Estampado%20con%20este%20Dise%C3%B1o%20%22ANM-11039%22"
    },
    {
        "sku": "ANM-11040",
        "keywords": " 40",
        "name": "MOD: ANM-11040",
        "hot": false,
        "new": false,
        "image": "https://i.ibb.co/d0cjPp25/ANIME-40.png",
        "link": "https://api.whatsapp.com/send?phone=2411576300&text=Hola!%20Me%20interesa%20un%20Estampado%20con%20este%20Dise%C3%B1o%20%22ANM-11040%22"
    },
    {
        "sku": "ANM-11041",
        "keywords": " 41",
        "name": "MOD: ANM-11041",
        "hot": false,
        "new": false,
        "image": "https://i.ibb.co/MDCK8JJs/ANIME-41.png",
        "link": "https://api.whatsapp.com/send?phone=2411576300&text=Hola!%20Me%20interesa%20un%20Estampado%20con%20este%20Dise%C3%B1o%20%22ANM-11041%22"
    },
    {
        "sku": "ANM-11042",
        "keywords": " 42",
        "name": "MOD: ANM-11042",
        "hot": false,
        "new": false,
        "image": "https://i.ibb.co/ks0dTbFH/ANIME-42.png",
        "link": "https://api.whatsapp.com/send?phone=2411576300&text=Hola!%20Me%20interesa%20un%20Estampado%20con%20este%20Dise%C3%B1o%20%22ANM-11042%22"
    },
    {
        "sku": "ANM-11043",
        "keywords": " 43",
        "name": "MOD: ANM-11043",
        "hot": false,
        "new": false,
        "image": "https://i.ibb.co/VczVBdNH/ANIME-43.png",
        "link": "https://api.whatsapp.com/send?phone=2411576300&text=Hola!%20Me%20interesa%20un%20Estampado%20con%20este%20Dise%C3%B1o%20%22ANM-11043%22"
    },
    {
        "sku": "ANM-11044",
        "keywords": " 44",
        "name": "MOD: ANM-11044",
        "hot": false,
        "new": false,
        "image": "https://i.ibb.co/dJ4hWgj0/ANIME-44.png",
        "link": "https://api.whatsapp.com/send?phone=2411576300&text=Hola!%20Me%20interesa%20un%20Estampado%20con%20este%20Dise%C3%B1o%20%22ANM-11044%22"
    },
    {
        "sku": "ANM-11045",
        "keywords": " 45",
        "name": "MOD: ANM-11045",
        "hot": false,
        "new": false,
        "image": "https://i.ibb.co/Lz1kfgnS/ANIME-45.png",
        "link": "https://api.whatsapp.com/send?phone=2411576300&text=Hola!%20Me%20interesa%20un%20Estampado%20con%20este%20Dise%C3%B1o%20%22ANM-11045%22"
    },
    {
        "sku": "ANM-11046",
        "keywords": " 46",
        "name": "MOD: ANM-11046",
        "hot": false,
        "new": false,
        "image": "https://i.ibb.co/BV3ykhr8/ANIME-46.png",
        "link": "https://api.whatsapp.com/send?phone=2411576300&text=Hola!%20Me%20interesa%20un%20Estampado%20con%20este%20Dise%C3%B1o%20%22ANM-11046%22"
    },
    {
        "sku": "ANM-11047",
        "keywords": " 47",
        "name": "MOD: ANM-11047",
        "hot": false,
        "new": false,
        "image": "https://i.ibb.co/wZRQhLnG/ANIME-47.png",
        "link": "https://api.whatsapp.com/send?phone=2411576300&text=Hola!%20Me%20interesa%20un%20Estampado%20con%20este%20Dise%C3%B1o%20%22ANM-11047%22"
    },
    {
        "sku": "ANM-11048",
        "keywords": " 48",
        "name": "MOD: ANM-11048",
        "hot": false,
        "new": false,
        "image": "https://i.ibb.co/dwLjz2P4/ANIME-48.png",
        "link": "https://api.whatsapp.com/send?phone=2411576300&text=Hola!%20Me%20interesa%20un%20Estampado%20con%20este%20Dise%C3%B1o%20%22ANM-11048%22"
    },
    {
        "sku": "ANM-11049",
        "keywords": " 49",
        "name": "MOD: ANM-11049",
        "hot": false,
        "new": false,
        "image": "https://i.ibb.co/BH7gk9Zb/ANIME-49.png",
        "link": "https://api.whatsapp.com/send?phone=2411576300&text=Hola!%20Me%20interesa%20un%20Estampado%20con%20este%20Dise%C3%B1o%20%22ANM-11049%22"
    },
    {
        "sku": "ANM-11050",
        "keywords": " 50",
        "name": "MOD: ANM-11050",
        "hot": false,
        "new": false,
        "image": "https://i.ibb.co/ZzQf8XYx/ANIME-50.png",
        "link": "https://api.whatsapp.com/send?phone=2411576300&text=Hola!%20Me%20interesa%20un%20Estampado%20con%20este%20Dise%C3%B1o%20%22ANM-11050%22"
    }
]
