[
    {
        "sku": "EXC-50001",
        "keywords": "esclusivos anime 1",
        "name": "MOD: EXC-50001",
        "hot": false,
        "new": false,
        "image": "https://i.ibb.co/5g3V1nzZ/ANIME-01.png",
        "link": "https://api.whatsapp.com/send?phone=2411576300&text=Hola!%20Me%20interesa%20un%20Estampado%20con%20este%20Dise%C3%B1o%20%22EXC-50001%22"
    },
    {
        "sku": "EXC-50002",
        "keywords": "esclusivos anime 2",
        "name": "MOD: EXC-50002",
        "hot": false,
        "new": false,
        "image": "https://i.ibb.co/yF3519J2/ANIME-02.png",
        "link": "https://api.whatsapp.com/send?phone=2411576300&text=Hola!%20Me%20interesa%20un%20Estampado%20con%20este%20Dise%C3%B1o%20%22EXC-50002%22"
    },
    {
        "sku": "EXC-50003",
        "keywords": "esclusivos anime 3",
        "name": "MOD: EXC-50003",
        "hot": false,
        "new": false,
        "image": "https://i.ibb.co/vxfnd3hz/ANIME-03.png",
        "link": "https://api.whatsapp.com/send?phone=2411576300&text=Hola!%20Me%20interesa%20un%20Estampado%20con%20este%20Dise%C3%B1o%20%22EXC-50003%22"
    },
    {
        "sku": "EXC-50004",
        "keywords": "esclusivos anime 4",
        "name": "MOD: EXC-50004",
        "hot": false,
        "new": false,
        "image": "https://i.ibb.co/2YW08sL6/ANIME-04.png",
        "link": "https://api.whatsapp.com/send?phone=2411576300&text=Hola!%20Me%20interesa%20un%20Estampado%20con%20este%20Dise%C3%B1o%20%22EXC-50004%22"
    },
    {
        "sku": "EXC-50005",
        "keywords": "esclusivos anime 5",
        "name": "MOD: EXC-50005",
        "hot": false,
        "new": false,
        "image": "https://i.ibb.co/1HMn8nV/ANIME-05.png",
        "link": "https://api.whatsapp.com/send?phone=2411576300&text=Hola!%20Me%20interesa%20un%20Estampado%20con%20este%20Dise%C3%B1o%20%22EXC-50005%22"
    },
    {
        "sku": "EXC-50006",
        "keywords": "esclusivos anime 6",
        "name": "MOD: EXC-50006",
        "hot": false,
        "new": false,
        "image": "https://i.ibb.co/Psbz3GFm/ANIME-06.png",
        "link": "https://api.whatsapp.com/send?phone=2411576300&text=Hola!%20Me%20interesa%20un%20Estampado%20con%20este%20Dise%C3%B1o%20%22EXC-50006%22"
    },
    {
        "sku": "EXC-50007",
        "keywords": "esclusivos anime 7",
        "name": "MOD: EXC-50007",
        "hot": false,
        "new": false,
        "image": "https://i.ibb.co/ks90tML6/ANIME-07.png",
        "link": "https://api.whatsapp.com/send?phone=2411576300&text=Hola!%20Me%20interesa%20un%20Estampado%20con%20este%20Dise%C3%B1o%20%22EXC-50007%22"
    },
    {
        "sku": "EXC-50008",
        "keywords": "esclusivos anime 8",
        "name": "MOD: EXC-50008",
        "hot": false,
        "new": false,
        "image": "https://i.ibb.co/B55c2L6q/ANIME-08.png",
        "link": "https://api.whatsapp.com/send?phone=2411576300&text=Hola!%20Me%20interesa%20un%20Estampado%20con%20este%20Dise%C3%B1o%20%22EXC-50008%22"
    },
    {
        "sku": "EXC-50009",
        "keywords": "esclusivos anime 9",
        "name": "MOD: EXC-50009",
        "hot": false,
        "new": false,
        "image": "https://i.ibb.co/V0vcjmG4/ANIME-09.png",
        "link": "https://api.whatsapp.com/send?phone=2411576300&text=Hola!%20Me%20interesa%20un%20Estampado%20con%20este%20Dise%C3%B1o%20%22EXC-50009%22"
    },
    {
        "sku": "EXC-50010",
        "keywords": "esclusivos anime 10",
        "name": "MOD: EXC-50010",
        "hot": false,
        "new": false,
        "image": "https://i.ibb.co/Q3mzD8LS/ANIME-10.png",
        "link": "https://api.whatsapp.com/send?phone=2411576300&text=Hola!%20Me%20interesa%20un%20Estampado%20con%20este%20Dise%C3%B1o%20%22EXC-50010%22"
    },
    {
        "sku": "EXC-50011",
        "keywords": "esclusivos anime 11",
        "name": "MOD: EXC-50011",
        "hot": false,
        "new": false,
        "image": "https://i.ibb.co/DgGpLfYZ/ANIME-11.png",
        "link": "https://api.whatsapp.com/send?phone=2411576300&text=Hola!%20Me%20interesa%20un%20Estampado%20con%20este%20Dise%C3%B1o%20%22EXC-50011%22"
    }
]