[
    {
        "sku": "EXC-02001",
        "keywords": "exclusivos anime 1",
        "name": "MOD: EXC-02001",
        "hot": false,
        "new": false,
        "image": "https://i.ibb.co/ycs69NTT/EXCLUSIVOS-01.png",
        "link": "https://api.whatsapp.com/send?phone=2411576300&text=Hola!%20Me%20interesa%20un%20Estampado%20con%20este%20Dise%C3%B1o%20%22EXC-02001%22"
    },
    {
        "sku": "EXC-02002",
        "keywords": "exclusivos anime 2",
        "name": "MOD: EXC-02002",
        "hot": false,
        "new": false,
        "image": "https://i.ibb.co/XZ05PWFY/EXCLUSIVOS-02.png",
        "link": "https://api.whatsapp.com/send?phone=2411576300&text=Hola!%20Me%20interesa%20un%20Estampado%20con%20este%20Dise%C3%B1o%20%22EXC-02002%22"
    },
    {
        "sku": "EXC-02003",
        "keywords": "exclusivos anime 3",
        "name": "MOD: EXC-02003",
        "hot": false,
        "new": false,
        "image": "https://i.ibb.co/9kJtvhKt/EXCLUSIVOS-03.png",
        "link": "https://api.whatsapp.com/send?phone=2411576300&text=Hola!%20Me%20interesa%20un%20Estampado%20con%20este%20Dise%C3%B1o%20%22EXC-02003%22"
    },
    {
        "sku": "EXC-02004",
        "keywords": "exclusivos anime 4",
        "name": "MOD: EXC-02004",
        "hot": false,
        "new": false,
        "image": "https://i.ibb.co/Kj3N9JxT/EXCLUSIVOS-04.png",
        "link": "https://api.whatsapp.com/send?phone=2411576300&text=Hola!%20Me%20interesa%20un%20Estampado%20con%20este%20Dise%C3%B1o%20%22EXC-02004%22"
    },
    {
        "sku": "EXC-02005",
        "keywords": "exclusivos anime 5",
        "name": "MOD: EXC-02005",
        "hot": false,
        "new": false,
        "image": "https://i.ibb.co/G40xQWSv/EXCLUSIVOS-05.png",
        "link": "https://api.whatsapp.com/send?phone=2411576300&text=Hola!%20Me%20interesa%20un%20Estampado%20con%20este%20Dise%C3%B1o%20%22EXC-02005%22"
    },
    {
        "sku": "EXC-02006",
        "keywords": "exclusivos anime 6",
        "name": "MOD: EXC-02006",
        "hot": false,
        "new": false,
        "image": "https://i.ibb.co/Q7SjDcxW/EXCLUSIVOS-06.png",
        "link": "https://api.whatsapp.com/send?phone=2411576300&text=Hola!%20Me%20interesa%20un%20Estampado%20con%20este%20Dise%C3%B1o%20%22EXC-02006%22"
    },
    {
        "sku": "EXC-02007",
        "keywords": "exclusivos anime 7",
        "name": "MOD: EXC-02007",
        "hot": false,
        "new": false,
        "image": "https://i.ibb.co/kV3Gksts/EXCLUSIVOS-07.png",
        "link": "https://api.whatsapp.com/send?phone=2411576300&text=Hola!%20Me%20interesa%20un%20Estampado%20con%20este%20Dise%C3%B1o%20%22EXC-02007%22"
    },
    {
        "sku": "EXC-02008",
        "keywords": "exclusivos anime 8",
        "name": "MOD: EXC-02008",
        "hot": false,
        "new": false,
        "image": "https://i.ibb.co/Z6QWr9vG/EXCLUSIVOS-08.png",
        "link": "https://api.whatsapp.com/send?phone=2411576300&text=Hola!%20Me%20interesa%20un%20Estampado%20con%20este%20Dise%C3%B1o%20%22EXC-02008%22"
    },
    {
        "sku": "EXC-02009",
        "keywords": "exclusivos anime 9",
        "name": "MOD: EXC-02009",
        "hot": false,
        "new": false,
        "image": "https://i.ibb.co/dw2fR1Jd/EXCLUSIVOS-09.png",
        "link": "https://api.whatsapp.com/send?phone=2411576300&text=Hola!%20Me%20interesa%20un%20Estampado%20con%20este%20Dise%C3%B1o%20%22EXC-02009%22"
    },
    {
        "sku": "EXC-02010",
        "keywords": "exclusivos anime 10",
        "name": "MOD: EXC-02010",
        "hot": false,
        "new": false,
        "image": "https://i.ibb.co/fzyzdPFb/EXCLUSIVOS-10.png",
        "link": "https://api.whatsapp.com/send?phone=2411576300&text=Hola!%20Me%20interesa%20un%20Estampado%20con%20este%20Dise%C3%B1o%20%22EXC-02010%22"
    },
    {
        "sku": "EXC-02011",
        "keywords": "exclusivos anime 11",
        "name": "MOD: EXC-02011",
        "hot": false,
        "new": false,
        "image": "https://i.ibb.co/hJWtwyjx/EXCLUSIVOS-11.png",
        "link": "https://api.whatsapp.com/send?phone=2411576300&text=Hola!%20Me%20interesa%20un%20Estampado%20con%20este%20Dise%C3%B1o%20%22EXC-02011%22"
    },
    {
        "sku": "EXC-02012",
        "keywords": "exclusivos anime 12",
        "name": "MOD: EXC-02012",
        "hot": false,
        "new": false,
        "image": "https://i.ibb.co/0RzBHwLd/EXCLUSIVOS-12.png",
        "link": "https://api.whatsapp.com/send?phone=2411576300&text=Hola!%20Me%20interesa%20un%20Estampado%20con%20este%20Dise%C3%B1o%20%22EXC-02012%22"
    },
    {
        "sku": "EXC-02013",
        "keywords": "exclusivos anime 13",
        "name": "MOD: EXC-02013",
        "hot": false,
        "new": false,
        "image": "https://i.ibb.co/cKLQms7D/EXCLUSIVOS-13.png",
        "link": "https://api.whatsapp.com/send?phone=2411576300&text=Hola!%20Me%20interesa%20un%20Estampado%20con%20este%20Dise%C3%B1o%20%22EXC-02013%22"
    }
]