[
    {
        "sku": "EXC-58001",
        "keywords": "esclusivos anime 1",
        "name": "MOD: EXC-58001",
        "hot": false,
        "new": false,
        "image": "https://i.ibb.co/vpDBDJZ/ANIME-01.png",
        "link": "https://api.whatsapp.com/send?phone=2411576300&text=Hola!%20Me%20interesa%20un%20Estampado%20con%20este%20Dise%C3%B1o%20%22EXC-58001%22"
    },
    {
        "sku": "EXC-58002",
        "keywords": "esclusivos anime 2",
        "name": "MOD: EXC-58002",
        "hot": false,
        "new": false,
        "image": "https://i.ibb.co/gF4yGp21/ANIME-02.png",
        "link": "https://api.whatsapp.com/send?phone=2411576300&text=Hola!%20Me%20interesa%20un%20Estampado%20con%20este%20Dise%C3%B1o%20%22EXC-58002%22"
    },
    {
        "sku": "EXC-58003",
        "keywords": "esclusivos anime 3",
        "name": "MOD: EXC-58003",
        "hot": false,
        "new": false,
        "image": "https://i.ibb.co/bjdbWd8p/ANIME-03.png",
        "link": "https://api.whatsapp.com/send?phone=2411576300&text=Hola!%20Me%20interesa%20un%20Estampado%20con%20este%20Dise%C3%B1o%20%22EXC-58003%22"
    },
    {
        "sku": "EXC-58004",
        "keywords": "esclusivos anime 4",
        "name": "MOD: EXC-58004",
        "hot": false,
        "new": false,
        "image": "https://i.ibb.co/Kp96Hyk0/ANIME-04.png",
        "link": "https://api.whatsapp.com/send?phone=2411576300&text=Hola!%20Me%20interesa%20un%20Estampado%20con%20este%20Dise%C3%B1o%20%22EXC-58004%22"
    },
    {
        "sku": "EXC-58005",
        "keywords": "esclusivos anime 5",
        "name": "MOD: EXC-58005",
        "hot": false,
        "new": false,
        "image": "https://i.ibb.co/BVHF6SkZ/ANIME-05.png",
        "link": "https://api.whatsapp.com/send?phone=2411576300&text=Hola!%20Me%20interesa%20un%20Estampado%20con%20este%20Dise%C3%B1o%20%22EXC-58005%22"
    },
    {
        "sku": "EXC-58006",
        "keywords": "esclusivos anime 6",
        "name": "MOD: EXC-58006",
        "hot": false,
        "new": false,
        "image": "https://i.ibb.co/k6y8tSns/ANIME-06.png",
        "link": "https://api.whatsapp.com/send?phone=2411576300&text=Hola!%20Me%20interesa%20un%20Estampado%20con%20este%20Dise%C3%B1o%20%22EXC-58006%22"
    },
    {
        "sku": "EXC-58007",
        "keywords": "esclusivos anime 7",
        "name": "MOD: EXC-58007",
        "hot": false,
        "new": false,
        "image": "https://i.ibb.co/JFCFc489/ANIME-07.png",
        "link": "https://api.whatsapp.com/send?phone=2411576300&text=Hola!%20Me%20interesa%20un%20Estampado%20con%20este%20Dise%C3%B1o%20%22EXC-58007%22"
    },
    {
        "sku": "EXC-58008",
        "keywords": "esclusivos anime 8",
        "name": "MOD: EXC-58008",
        "hot": false,
        "new": false,
        "image": "https://i.ibb.co/hxZ5X1FY/ANIME-08.png",
        "link": "https://api.whatsapp.com/send?phone=2411576300&text=Hola!%20Me%20interesa%20un%20Estampado%20con%20este%20Dise%C3%B1o%20%22EXC-58008%22"
    },
    {
        "sku": "EXC-58009",
        "keywords": "esclusivos anime 9",
        "name": "MOD: EXC-58009",
        "hot": false,
        "new": false,
        "image": "https://i.ibb.co/LXQRXx68/ANIME-09.png",
        "link": "https://api.whatsapp.com/send?phone=2411576300&text=Hola!%20Me%20interesa%20un%20Estampado%20con%20este%20Dise%C3%B1o%20%22EXC-58009%22"
    },
    {
        "sku": "EXC-58010",
        "keywords": "esclusivos anime 10",
        "name": "MOD: EXC-58010",
        "hot": false,
        "new": false,
        "image": "https://i.ibb.co/4Ztpdb3W/ANIME-10.png",
        "link": "https://api.whatsapp.com/send?phone=2411576300&text=Hola!%20Me%20interesa%20un%20Estampado%20con%20este%20Dise%C3%B1o%20%22EXC-58010%22"
    }
]