[
    {
        "sku": "PKM-04001",
        "keywords": "anime pokemon ash pikachu 1",
        "name": "MOD: PKM-04001",
        "hot": false,
        "new": false,
        "image": "https://i.ibb.co/21yR8F4N/BULBASAUR.png",
        "link": "https://api.whatsapp.com/send?phone=2411576300&text=Hola!%20Me%20interesa%20un%20Estampado%20con%20este%20Dise%C3%B1o%20%22PKM-04001%22"
    },
    {
        "sku": "PKM-04002",
        "keywords": "anime pokemon ash pikachu 2",
        "name": "MOD: PKM-04002",
        "hot": false,
        "new": false,
        "image": "https://i.ibb.co/KpwYsMG5/CHARIZARD.png",
        "link": "https://api.whatsapp.com/send?phone=2411576300&text=Hola!%20Me%20interesa%20un%20Estampado%20con%20este%20Dise%C3%B1o%20%22PKM-04002%22"
    },
    {
        "sku": "PKM-04003",
        "keywords": "anime pokemon ash pikachu 3",
        "name": "MOD: PKM-04003",
        "hot": false,
        "new": false,
        "image": "https://i.ibb.co/vCxNvNb1/CHARMANDER.png",
        "link": "https://api.whatsapp.com/send?phone=2411576300&text=Hola!%20Me%20interesa%20un%20Estampado%20con%20este%20Dise%C3%B1o%20%22PKM-04003%22"
    },
    {
        "sku": "PKM-04004",
        "keywords": "anime pokemon ash pikachu 4",
        "name": "MOD: PKM-04004",
        "hot": false,
        "new": false,
        "image": "https://i.ibb.co/bjwc5KBG/CUBONE.png",
        "link": "https://api.whatsapp.com/send?phone=2411576300&text=Hola!%20Me%20interesa%20un%20Estampado%20con%20este%20Dise%C3%B1o%20%22PKM-04004%22"
    },
    {
        "sku": "PKM-04005",
        "keywords": "anime pokemon ash pikachu 5",
        "name": "MOD: PKM-04005",
        "hot": false,
        "new": false,
        "image": "https://i.ibb.co/pvtbX9PR/DITO.png",
        "link": "https://api.whatsapp.com/send?phone=2411576300&text=Hola!%20Me%20interesa%20un%20Estampado%20con%20este%20Dise%C3%B1o%20%22PKM-04005%22"
    },
    {
        "sku": "PKM-04006",
        "keywords": "anime pokemon ash pikachu 6",
        "name": "MOD: PKM-04006",
        "hot": false,
        "new": false,
        "image": "https://i.ibb.co/JRJZLsTD/EEVEE.png",
        "link": "https://api.whatsapp.com/send?phone=2411576300&text=Hola!%20Me%20interesa%20un%20Estampado%20con%20este%20Dise%C3%B1o%20%22PKM-04006%22"
    },
    {
        "sku": "PKM-04007",
        "keywords": "anime pokemon ash pikachu 7",
        "name": "MOD: PKM-04007",
        "hot": false,
        "new": false,
        "image": "https://i.ibb.co/gKHw93p/FLAREON.png",
        "link": "https://api.whatsapp.com/send?phone=2411576300&text=Hola!%20Me%20interesa%20un%20Estampado%20con%20este%20Dise%C3%B1o%20%22PKM-04007%22"
    },
    {
        "sku": "PKM-04008",
        "keywords": "anime pokemon ash pikachu 8",
        "name": "MOD: PKM-04008",
        "hot": false,
        "new": false,
        "image": "https://i.ibb.co/w519kH9/GENGAR.png",
        "link": "https://api.whatsapp.com/send?phone=2411576300&text=Hola!%20Me%20interesa%20un%20Estampado%20con%20este%20Dise%C3%B1o%20%22PKM-04008%22"
    },
    {
        "sku": "PKM-04009",
        "keywords": "anime pokemon ash pikachu 9",
        "name": "MOD: PKM-04009",
        "hot": false,
        "new": false,
        "image": "https://i.ibb.co/20Svqtb5/GYARADOS.png",
        "link": "https://api.whatsapp.com/send?phone=2411576300&text=Hola!%20Me%20interesa%20un%20Estampado%20con%20este%20Dise%C3%B1o%20%22PKM-04009%22"
    },
    {
        "sku": "PKM-04010",
        "keywords": "anime pokemon ash pikachu 10",
        "name": "MOD: PKM-04010",
        "hot": false,
        "new": false,
        "image": "https://i.ibb.co/F4jzDvCq/HUEVOFET.png",
        "link": "https://api.whatsapp.com/send?phone=2411576300&text=Hola!%20Me%20interesa%20un%20Estampado%20con%20este%20Dise%C3%B1o%20%22PKM-04010%22"
    },
    {
        "sku": "PKM-04011",
        "keywords": "anime pokemon ash pikachu 11",
        "name": "MOD: PKM-04011",
        "hot": false,
        "new": false,
        "image": "https://i.ibb.co/Y4j99b2b/HUNTER.png",
        "link": "https://api.whatsapp.com/send?phone=2411576300&text=Hola!%20Me%20interesa%20un%20Estampado%20con%20este%20Dise%C3%B1o%20%22PKM-04011%22"
    },
    {
        "sku": "PKM-04012",
        "keywords": "anime pokemon ash pikachu 12",
        "name": "MOD: PKM-04012",
        "hot": false,
        "new": false,
        "image": "https://i.ibb.co/qMbXtR8r/JIGGLYPUFF-2.png",
        "link": "https://api.whatsapp.com/send?phone=2411576300&text=Hola!%20Me%20interesa%20un%20Estampado%20con%20este%20Dise%C3%B1o%20%22PKM-04012%22"
    },
    {
        "sku": "PKM-04013",
        "keywords": "anime pokemon ash pikachu 13",
        "name": "MOD: PKM-04013",
        "hot": false,
        "new": false,
        "image": "https://i.ibb.co/hR7R80Js/JIGGLYPUFF.png",
        "link": "https://api.whatsapp.com/send?phone=2411576300&text=Hola!%20Me%20interesa%20un%20Estampado%20con%20este%20Dise%C3%B1o%20%22PKM-04013%22"
    },
    {
        "sku": "PKM-04014",
        "keywords": "anime pokemon ash pikachu 14",
        "name": "MOD: PKM-04014",
        "hot": false,
        "new": false,
        "image": "https://i.ibb.co/VYyGK4GN/JOLTEON.png",
        "link": "https://api.whatsapp.com/send?phone=2411576300&text=Hola!%20Me%20interesa%20un%20Estampado%20con%20este%20Dise%C3%B1o%20%22PKM-04014%22"
    },
    {
        "sku": "PKM-04015",
        "keywords": "anime pokemon ash pikachu 15",
        "name": "MOD: PKM-04015",
        "hot": false,
        "new": false,
        "image": "https://i.ibb.co/bMW4F4mg/KOFFING.png",
        "link": "https://api.whatsapp.com/send?phone=2411576300&text=Hola!%20Me%20interesa%20un%20Estampado%20con%20este%20Dise%C3%B1o%20%22PKM-04015%22"
    },
    {
        "sku": "PKM-04016",
        "keywords": "anime pokemon ash pikachu 16",
        "name": "MOD: PKM-04016",
        "hot": false,
        "new": false,
        "image": "https://i.ibb.co/93cFGk5M/MAGIKARP.png",
        "link": "https://api.whatsapp.com/send?phone=2411576300&text=Hola!%20Me%20interesa%20un%20Estampado%20con%20este%20Dise%C3%B1o%20%22PKM-04016%22"
    },
    {
        "sku": "PKM-04017",
        "keywords": "anime pokemon ash pikachu 17",
        "name": "MOD: PKM-04017",
        "hot": false,
        "new": false,
        "image": "https://i.ibb.co/kPD21rf/MEOWTH.png",
        "link": "https://api.whatsapp.com/send?phone=2411576300&text=Hola!%20Me%20interesa%20un%20Estampado%20con%20este%20Dise%C3%B1o%20%22PKM-04017%22"
    },
    {
        "sku": "PKM-04018",
        "keywords": "anime pokemon ash pikachu 18",
        "name": "MOD: PKM-04018",
        "hot": false,
        "new": false,
        "image": "https://i.ibb.co/cdD07MD/MEWTWO.png",
        "link": "https://api.whatsapp.com/send?phone=2411576300&text=Hola!%20Me%20interesa%20un%20Estampado%20con%20este%20Dise%C3%B1o%20%22PKM-04018%22"
    },
    {
        "sku": "PKM-04019",
        "keywords": "anime pokemon ash pikachu 19",
        "name": "MOD: PKM-04019",
        "hot": false,
        "new": false,
        "image": "https://i.ibb.co/nNZWk95Z/PIKACHU.png",
        "link": "https://api.whatsapp.com/send?phone=2411576300&text=Hola!%20Me%20interesa%20un%20Estampado%20con%20este%20Dise%C3%B1o%20%22PKM-04019%22"
    },
    {
        "sku": "PKM-04020",
        "keywords": "anime pokemon ash pikachu 20",
        "name": "MOD: PKM-04020",
        "hot": false,
        "new": false,
        "image": "https://i.ibb.co/93n0mLfW/PSYDUCK.png",
        "link": "https://api.whatsapp.com/send?phone=2411576300&text=Hola!%20Me%20interesa%20un%20Estampado%20con%20este%20Dise%C3%B1o%20%22PKM-04020%22"
    },
    {
        "sku": "PKM-04021",
        "keywords": "anime pokemon ash pikachu 21",
        "name": "MOD: PKM-04021",
        "hot": false,
        "new": false,
        "image": "https://i.ibb.co/Q3PDt5T8/RAICHU.png",
        "link": "https://api.whatsapp.com/send?phone=2411576300&text=Hola!%20Me%20interesa%20un%20Estampado%20con%20este%20Dise%C3%B1o%20%22PKM-04021%22"
    },
    {
        "sku": "PKM-04022",
        "keywords": "anime pokemon ash pikachu 22",
        "name": "MOD: PKM-04022",
        "hot": false,
        "new": false,
        "image": "https://i.ibb.co/PvBG4tVX/SLOWPOKE.png",
        "link": "https://api.whatsapp.com/send?phone=2411576300&text=Hola!%20Me%20interesa%20un%20Estampado%20con%20este%20Dise%C3%B1o%20%22PKM-04022%22"
    },
    {
        "sku": "PKM-04023",
        "keywords": "anime pokemon ash pikachu 23",
        "name": "MOD: PKM-04023",
        "hot": false,
        "new": false,
        "image": "https://i.ibb.co/FkxWX55N/SNORLAX.png",
        "link": "https://api.whatsapp.com/send?phone=2411576300&text=Hola!%20Me%20interesa%20un%20Estampado%20con%20este%20Dise%C3%B1o%20%22PKM-04023%22"
    },
    {
        "sku": "PKM-04024",
        "keywords": "anime pokemon ash pikachu 24",
        "name": "MOD: PKM-04024",
        "hot": false,
        "new": false,
        "image": "https://i.ibb.co/6cxbTBpD/SQUIRTLE-2.png",
        "link": "https://api.whatsapp.com/send?phone=2411576300&text=Hola!%20Me%20interesa%20un%20Estampado%20con%20este%20Dise%C3%B1o%20%22PKM-04024%22"
    },
    {
        "sku": "PKM-04025",
        "keywords": "anime pokemon ash pikachu 25",
        "name": "MOD: PKM-04025",
        "hot": false,
        "new": false,
        "image": "https://i.ibb.co/W9Xpf8r/SQUIRTLE.png",
        "link": "https://api.whatsapp.com/send?phone=2411576300&text=Hola!%20Me%20interesa%20un%20Estampado%20con%20este%20Dise%C3%B1o%20%22PKM-04025%22"
    },
    {
        "sku": "PKM-04026",
        "keywords": "anime pokemon ash pikachu 26",
        "name": "MOD: PKM-04026",
        "hot": false,
        "new": false,
        "image": "https://i.ibb.co/rKbgxmZD/TOGEPI.png",
        "link": "https://api.whatsapp.com/send?phone=2411576300&text=Hola!%20Me%20interesa%20un%20Estampado%20con%20este%20Dise%C3%B1o%20%22PKM-04026%22"
    },
    {
        "sku": "PKM-04027",
        "keywords": "anime pokemon ash pikachu 27",
        "name": "MOD: PKM-04027",
        "hot": false,
        "new": false,
        "image": "https://i.ibb.co/7xP2KVsz/VAPOREON.png",
        "link": "https://api.whatsapp.com/send?phone=2411576300&text=Hola!%20Me%20interesa%20un%20Estampado%20con%20este%20Dise%C3%B1o%20%22PKM-04027%22"
    },
    {
        "sku": "PKM-04028",
        "keywords": "anime pokemon ash pikachu 28",
        "name": "MOD: PKM-04028",
        "hot": false,
        "new": false,
        "image": "https://i.ibb.co/2769qy21/VULPIX.png",
        "link": "https://api.whatsapp.com/send?phone=2411576300&text=Hola!%20Me%20interesa%20un%20Estampado%20con%20este%20Dise%C3%B1o%20%22PKM-04028%22"
    }
]