[
    {
        "sku": "SPR-01001",
        "keywords": "carros vehiculos racing carreras supra 1",
        "name": "MOD: SPR-01001",
        "hot": false,
        "new": false,
        "image": "https://i.ibb.co/Tq2Q024t/SUPRA-01.png",
        "link": "https://api.whatsapp.com/send?phone=2411576300&text=Hola!%20Me%20interesa%20un%20Estampado%20con%20este%20Dise%C3%B1o%20%22SPR-01001%22"
    },
    {
        "sku": "SPR-01002",
        "keywords": "carros vehiculos racing carreras supra 2",
        "name": "MOD: SPR-01002",
        "hot": false,
        "new": false,
        "image": "https://i.ibb.co/0jsV7xsT/SUPRA-02.png",
        "link": "https://api.whatsapp.com/send?phone=2411576300&text=Hola!%20Me%20interesa%20un%20Estampado%20con%20este%20Dise%C3%B1o%20%22SPR-01002%22"
    },
    {
        "sku": "SPR-01003",
        "keywords": "carros vehiculos racing carreras supra 3",
        "name": "MOD: SPR-01003",
        "hot": false,
        "new": false,
        "image": "https://i.ibb.co/bRHpW99c/SUPRA-03.png",
        "link": "https://api.whatsapp.com/send?phone=2411576300&text=Hola!%20Me%20interesa%20un%20Estampado%20con%20este%20Dise%C3%B1o%20%22SPR-01003%22"
    },
    {
        "sku": "SPR-01004",
        "keywords": "carros vehiculos racing carreras supra 4",
        "name": "MOD: SPR-01004",
        "hot": false,
        "new": false,
        "image": "https://i.ibb.co/1ft1MNdp/SUPRA-04.png",
        "link": "https://api.whatsapp.com/send?phone=2411576300&text=Hola!%20Me%20interesa%20un%20Estampado%20con%20este%20Dise%C3%B1o%20%22SPR-01004%22"
    },
    {
        "sku": "SPR-01005",
        "keywords": "carros vehiculos racing carreras supra 5",
        "name": "MOD: SPR-01005",
        "hot": false,
        "new": false,
        "image": "https://i.ibb.co/bqFfrq7/SUPRA-05.png",
        "link": "https://api.whatsapp.com/send?phone=2411576300&text=Hola!%20Me%20interesa%20un%20Estampado%20con%20este%20Dise%C3%B1o%20%22SPR-01005%22"
    },
    {
        "sku": "SPR-01006",
        "keywords": "carros vehiculos racing carreras supra 6",
        "name": "MOD: SPR-01006",
        "hot": false,
        "new": false,
        "image": "https://i.ibb.co/dsLB42KL/SUPRA-06.png",
        "link": "https://api.whatsapp.com/send?phone=2411576300&text=Hola!%20Me%20interesa%20un%20Estampado%20con%20este%20Dise%C3%B1o%20%22SPR-01006%22"
    }
]