[
    {
        "sku": "URB-31001",
        "keywords": "urbanos 1",
        "name": "MOD: URB-31001",
        "hot": false,
        "new": false,
        "image": "https://i.ibb.co/Y4LXmZt6/URBANO-01.png",
        "link": "https://api.whatsapp.com/send?phone=2411576300&text=Hola!%20Me%20interesa%20un%20Estampado%20con%20este%20Dise%C3%B1o%20%22URB-31001%22"
    },
    {
        "sku": "URB-31002",
        "keywords": "urbanos 2",
        "name": "MOD: URB-31002",
        "hot": false,
        "new": false,
        "image": "https://i.ibb.co/sp8vCZVx/URBANO-02.png",
        "link": "https://api.whatsapp.com/send?phone=2411576300&text=Hola!%20Me%20interesa%20un%20Estampado%20con%20este%20Dise%C3%B1o%20%22URB-31002%22"
    },
    {
        "sku": "URB-31003",
        "keywords": "urbanos 3",
        "name": "MOD: URB-31003",
        "hot": false,
        "new": false,
        "image": "https://i.ibb.co/4RqGyLHT/URBANO-03.png",
        "link": "https://api.whatsapp.com/send?phone=2411576300&text=Hola!%20Me%20interesa%20un%20Estampado%20con%20este%20Dise%C3%B1o%20%22URB-31003%22"
    },
    {
        "sku": "URB-31004",
        "keywords": "urbanos 4",
        "name": "MOD: URB-31004",
        "hot": false,
        "new": false,
        "image": "https://i.ibb.co/hRpqy6xS/URBANO-04.png",
        "link": "https://api.whatsapp.com/send?phone=2411576300&text=Hola!%20Me%20interesa%20un%20Estampado%20con%20este%20Dise%C3%B1o%20%22URB-31004%22"
    },
    {
        "sku": "URB-31005",
        "keywords": "urbanos 5",
        "name": "MOD: URB-31005",
        "hot": false,
        "new": false,
        "image": "https://i.ibb.co/kV5JjdCw/URBANO-05.png",
        "link": "https://api.whatsapp.com/send?phone=2411576300&text=Hola!%20Me%20interesa%20un%20Estampado%20con%20este%20Dise%C3%B1o%20%22URB-31005%22"
    },
    {
        "sku": "URB-31006",
        "keywords": "urbanos 6",
        "name": "MOD: URB-31006",
        "hot": false,
        "new": false,
        "image": "https://i.ibb.co/Gv64NKwG/URBANO-06.png",
        "link": "https://api.whatsapp.com/send?phone=2411576300&text=Hola!%20Me%20interesa%20un%20Estampado%20con%20este%20Dise%C3%B1o%20%22URB-31006%22"
    },
    {
        "sku": "URB-31007",
        "keywords": "urbanos 7",
        "name": "MOD: URB-31007",
        "hot": false,
        "new": false,
        "image": "https://i.ibb.co/TBXkyD7L/URBANO-07.png",
        "link": "https://api.whatsapp.com/send?phone=2411576300&text=Hola!%20Me%20interesa%20un%20Estampado%20con%20este%20Dise%C3%B1o%20%22URB-31007%22"
    },
    {
        "sku": "URB-31008",
        "keywords": "urbanos 8",
        "name": "MOD: URB-31008",
        "hot": false,
        "new": false,
        "image": "https://i.ibb.co/MxbP9Pxk/URBANO-08.png",
        "link": "https://api.whatsapp.com/send?phone=2411576300&text=Hola!%20Me%20interesa%20un%20Estampado%20con%20este%20Dise%C3%B1o%20%22URB-31008%22"
    },
    {
        "sku": "URB-31009",
        "keywords": "urbanos 9",
        "name": "MOD: URB-31009",
        "hot": false,
        "new": false,
        "image": "https://i.ibb.co/nsSyd9XJ/URBANO-09.png",
        "link": "https://api.whatsapp.com/send?phone=2411576300&text=Hola!%20Me%20interesa%20un%20Estampado%20con%20este%20Dise%C3%B1o%20%22URB-31009%22"
    },
    {
        "sku": "URB-31010",
        "keywords": "urbanos 10",
        "name": "MOD: URB-31010",
        "hot": false,
        "new": false,
        "image": "https://i.ibb.co/SX8b38TJ/URBANO-10.png",
        "link": "https://api.whatsapp.com/send?phone=2411576300&text=Hola!%20Me%20interesa%20un%20Estampado%20con%20este%20Dise%C3%B1o%20%22URB-31010%22"
    },
    {
        "sku": "URB-31011",
        "keywords": "urbanos 11",
        "name": "MOD: URB-31011",
        "hot": false,
        "new": false,
        "image": "https://i.ibb.co/0yxXhN71/URBANO-11.png",
        "link": "https://api.whatsapp.com/send?phone=2411576300&text=Hola!%20Me%20interesa%20un%20Estampado%20con%20este%20Dise%C3%B1o%20%22URB-31011%22"
    },
    {
        "sku": "URB-31012",
        "keywords": "urbanos 12",
        "name": "MOD: URB-31012",
        "hot": false,
        "new": false,
        "image": "https://i.ibb.co/NdS3gwDb/URBANO-12.png",
        "link": "https://api.whatsapp.com/send?phone=2411576300&text=Hola!%20Me%20interesa%20un%20Estampado%20con%20este%20Dise%C3%B1o%20%22URB-31012%22"
    },
    {
        "sku": "URB-31013",
        "keywords": "urbanos 13",
        "name": "MOD: URB-31013",
        "hot": false,
        "new": false,
        "image": "https://i.ibb.co/m5YpGJ6g/URBANO-13.png",
        "link": "https://api.whatsapp.com/send?phone=2411576300&text=Hola!%20Me%20interesa%20un%20Estampado%20con%20este%20Dise%C3%B1o%20%22URB-31013%22"
    },
    {
        "sku": "URB-31014",
        "keywords": "urbanos 14",
        "name": "MOD: URB-31014",
        "hot": false,
        "new": false,
        "image": "https://i.ibb.co/21zB597q/URBANO-14.png",
        "link": "https://api.whatsapp.com/send?phone=2411576300&text=Hola!%20Me%20interesa%20un%20Estampado%20con%20este%20Dise%C3%B1o%20%22URB-31014%22"
    },
    {
        "sku": "URB-31015",
        "keywords": "urbanos 15",
        "name": "MOD: URB-31015",
        "hot": false,
        "new": false,
        "image": "https://i.ibb.co/sJCymq3w/URBANO-15.png",
        "link": "https://api.whatsapp.com/send?phone=2411576300&text=Hola!%20Me%20interesa%20un%20Estampado%20con%20este%20Dise%C3%B1o%20%22URB-31015%22"
    },
    {
        "sku": "URB-31016",
        "keywords": "urbanos 16",
        "name": "MOD: URB-31016",
        "hot": false,
        "new": false,
        "image": "https://i.ibb.co/YFk4x9n7/URBANO-16.png",
        "link": "https://api.whatsapp.com/send?phone=2411576300&text=Hola!%20Me%20interesa%20un%20Estampado%20con%20este%20Dise%C3%B1o%20%22URB-31016%22"
    },
    {
        "sku": "URB-31017",
        "keywords": "urbanos 17",
        "name": "MOD: URB-31017",
        "hot": false,
        "new": false,
        "image": "https://i.ibb.co/20cs7X52/URBANO-17.png",
        "link": "https://api.whatsapp.com/send?phone=2411576300&text=Hola!%20Me%20interesa%20un%20Estampado%20con%20este%20Dise%C3%B1o%20%22URB-31017%22"
    },
    {
        "sku": "URB-31018",
        "keywords": "urbanos 18",
        "name": "MOD: URB-31018",
        "hot": false,
        "new": false,
        "image": "https://i.ibb.co/cnwgs4D/URBANO-18.png",
        "link": "https://api.whatsapp.com/send?phone=2411576300&text=Hola!%20Me%20interesa%20un%20Estampado%20con%20este%20Dise%C3%B1o%20%22URB-31018%22"
    },
    {
        "sku": "URB-31019",
        "keywords": "urbanos 19",
        "name": "MOD: URB-31019",
        "hot": false,
        "new": false,
        "image": "https://i.ibb.co/dwDd6BX6/URBANO-19.png",
        "link": "https://api.whatsapp.com/send?phone=2411576300&text=Hola!%20Me%20interesa%20un%20Estampado%20con%20este%20Dise%C3%B1o%20%22URB-31019%22"
    },
    {
        "sku": "URB-31020",
        "keywords": "urbanos 20",
        "name": "MOD: URB-31020",
        "hot": false,
        "new": false,
        "image": "https://i.ibb.co/zTdLxr4h/URBANO-20.png",
        "link": "https://api.whatsapp.com/send?phone=2411576300&text=Hola!%20Me%20interesa%20un%20Estampado%20con%20este%20Dise%C3%B1o%20%22URB-31020%22"
    },
    {
        "sku": "URB-31021",
        "keywords": "urbanos 21",
        "name": "MOD: URB-31021",
        "hot": false,
        "new": false,
        "image": "https://i.ibb.co/1G1t6Zhc/URBANO-21.png",
        "link": "https://api.whatsapp.com/send?phone=2411576300&text=Hola!%20Me%20interesa%20un%20Estampado%20con%20este%20Dise%C3%B1o%20%22URB-31021%22"
    },
    {
        "sku": "URB-31022",
        "keywords": "urbanos 22",
        "name": "MOD: URB-31022",
        "hot": false,
        "new": false,
        "image": "https://i.ibb.co/wrzqWRdp/URBANO-22.png",
        "link": "https://api.whatsapp.com/send?phone=2411576300&text=Hola!%20Me%20interesa%20un%20Estampado%20con%20este%20Dise%C3%B1o%20%22URB-31022%22"
    },
    {
        "sku": "URB-31023",
        "keywords": "urbanos 23",
        "name": "MOD: URB-31023",
        "hot": false,
        "new": false,
        "image": "https://i.ibb.co/vxWJ66HC/URBANO-23.png",
        "link": "https://api.whatsapp.com/send?phone=2411576300&text=Hola!%20Me%20interesa%20un%20Estampado%20con%20este%20Dise%C3%B1o%20%22URB-31023%22"
    },
    {
        "sku": "URB-31024",
        "keywords": "urbanos 24",
        "name": "MOD: URB-31024",
        "hot": false,
        "new": false,
        "image": "https://i.ibb.co/hJQZBKyQ/URBANO-24.png",
        "link": "https://api.whatsapp.com/send?phone=2411576300&text=Hola!%20Me%20interesa%20un%20Estampado%20con%20este%20Dise%C3%B1o%20%22URB-31024%22"
    },
    {
        "sku": "URB-31025",
        "keywords": "urbanos 25",
        "name": "MOD: URB-31025",
        "hot": false,
        "new": false,
        "image": "https://i.ibb.co/cKphKVNY/URBANO-25.png",
        "link": "https://api.whatsapp.com/send?phone=2411576300&text=Hola!%20Me%20interesa%20un%20Estampado%20con%20este%20Dise%C3%B1o%20%22URB-31025%22"
    },
    {
        "sku": "URB-31026",
        "keywords": "urbanos 26",
        "name": "MOD: URB-31026",
        "hot": false,
        "new": false,
        "image": "https://i.ibb.co/Bk5Z9Sy/URBANO-26.png",
        "link": "https://api.whatsapp.com/send?phone=2411576300&text=Hola!%20Me%20interesa%20un%20Estampado%20con%20este%20Dise%C3%B1o%20%22URB-31026%22"
    },
    {
        "sku": "URB-31027",
        "keywords": "urbanos 27",
        "name": "MOD: URB-31027",
        "hot": false,
        "new": false,
        "image": "https://i.ibb.co/Fkmy0zP6/URBANO-27.png",
        "link": "https://api.whatsapp.com/send?phone=2411576300&text=Hola!%20Me%20interesa%20un%20Estampado%20con%20este%20Dise%C3%B1o%20%22URB-31027%22"
    },
    {
        "sku": "URB-31028",
        "keywords": "urbanos 28",
        "name": "MOD: URB-31028",
        "hot": false,
        "new": false,
        "image": "https://i.ibb.co/ZpHjjg6X/URBANO-28.png",
        "link": "https://api.whatsapp.com/send?phone=2411576300&text=Hola!%20Me%20interesa%20un%20Estampado%20con%20este%20Dise%C3%B1o%20%22URB-31028%22"
    },
    {
        "sku": "URB-31029",
        "keywords": "urbanos 29",
        "name": "MOD: URB-31029",
        "hot": false,
        "new": false,
        "image": "https://i.ibb.co/s9YV47PH/URBANO-29.png",
        "link": "https://api.whatsapp.com/send?phone=2411576300&text=Hola!%20Me%20interesa%20un%20Estampado%20con%20este%20Dise%C3%B1o%20%22URB-31029%22"
    },
    {
        "sku": "URB-31030",
        "keywords": "urbanos 30",
        "name": "MOD: URB-31030",
        "hot": false,
        "new": false,
        "image": "https://i.ibb.co/mCyCK4zL/URBANO-30.png",
        "link": "https://api.whatsapp.com/send?phone=2411576300&text=Hola!%20Me%20interesa%20un%20Estampado%20con%20este%20Dise%C3%B1o%20%22URB-31030%22"
    },
    {
        "sku": "URB-31031",
        "keywords": "urbanos 31",
        "name": "MOD: URB-31031",
        "hot": false,
        "new": false,
        "image": "https://i.ibb.co/spZP36tc/URBANO-31.png",
        "link": "https://api.whatsapp.com/send?phone=2411576300&text=Hola!%20Me%20interesa%20un%20Estampado%20con%20este%20Dise%C3%B1o%20%22URB-31031%22"
    },
    {
        "sku": "URB-31032",
        "keywords": "urbanos 32",
        "name": "MOD: URB-31032",
        "hot": false,
        "new": false,
        "image": "https://i.ibb.co/0yZ2dswD/URBANO-32.png",
        "link": "https://api.whatsapp.com/send?phone=2411576300&text=Hola!%20Me%20interesa%20un%20Estampado%20con%20este%20Dise%C3%B1o%20%22URB-31032%22"
    },
    {
        "sku": "URB-31033",
        "keywords": "urbanos 33",
        "name": "MOD: URB-31033",
        "hot": false,
        "new": false,
        "image": "https://i.ibb.co/d0G0md9h/URBANO-33.png",
        "link": "https://api.whatsapp.com/send?phone=2411576300&text=Hola!%20Me%20interesa%20un%20Estampado%20con%20este%20Dise%C3%B1o%20%22URB-31033%22"
    },
    {
        "sku": "URB-31034",
        "keywords": "urbanos 34",
        "name": "MOD: URB-31034",
        "hot": false,
        "new": false,
        "image": "https://i.ibb.co/4gXzghLp/URBANO-34.png",
        "link": "https://api.whatsapp.com/send?phone=2411576300&text=Hola!%20Me%20interesa%20un%20Estampado%20con%20este%20Dise%C3%B1o%20%22URB-31034%22"
    },
    {
        "sku": "URB-31035",
        "keywords": "urbanos 35",
        "name": "MOD: URB-31035",
        "hot": false,
        "new": false,
        "image": "https://i.ibb.co/VYGwxBkN/URBANO-35.png",
        "link": "https://api.whatsapp.com/send?phone=2411576300&text=Hola!%20Me%20interesa%20un%20Estampado%20con%20este%20Dise%C3%B1o%20%22URB-31035%22"
    },
    {
        "sku": "URB-31036",
        "keywords": "urbanos 36",
        "name": "MOD: URB-31036",
        "hot": false,
        "new": false,
        "image": "https://i.ibb.co/mFCWkbS3/URBANO-36.png",
        "link": "https://api.whatsapp.com/send?phone=2411576300&text=Hola!%20Me%20interesa%20un%20Estampado%20con%20este%20Dise%C3%B1o%20%22URB-31036%22"
    },
    {
        "sku": "URB-31037",
        "keywords": "urbanos 37",
        "name": "MOD: URB-31037",
        "hot": false,
        "new": false,
        "image": "https://i.ibb.co/nWWjHQW/URBANO-37.png",
        "link": "https://api.whatsapp.com/send?phone=2411576300&text=Hola!%20Me%20interesa%20un%20Estampado%20con%20este%20Dise%C3%B1o%20%22URB-31037%22"
    },
    {
        "sku": "URB-31038",
        "keywords": "urbanos 38",
        "name": "MOD: URB-31038",
        "hot": false,
        "new": false,
        "image": "https://i.ibb.co/4ndvVgWV/URBANO-38.png",
        "link": "https://api.whatsapp.com/send?phone=2411576300&text=Hola!%20Me%20interesa%20un%20Estampado%20con%20este%20Dise%C3%B1o%20%22URB-31038%22"
    },
    {
        "sku": "URB-31039",
        "keywords": "urbanos 39",
        "name": "MOD: URB-31039",
        "hot": false,
        "new": false,
        "image": "https://i.ibb.co/mrCwCcT6/URBANO-39.png",
        "link": "https://api.whatsapp.com/send?phone=2411576300&text=Hola!%20Me%20interesa%20un%20Estampado%20con%20este%20Dise%C3%B1o%20%22URB-31039%22"
    },
    {
        "sku": "URB-31040",
        "keywords": "urbanos 40",
        "name": "MOD: URB-31040",
        "hot": false,
        "new": false,
        "image": "https://i.ibb.co/Zz84VRX3/URBANO-40.png",
        "link": "https://api.whatsapp.com/send?phone=2411576300&text=Hola!%20Me%20interesa%20un%20Estampado%20con%20este%20Dise%C3%B1o%20%22URB-31040%22"
    },
    {
        "sku": "URB-31041",
        "keywords": "urbanos 41",
        "name": "MOD: URB-31041",
        "hot": false,
        "new": false,
        "image": "https://i.ibb.co/ZzPN0TJH/URBANO-41.png",
        "link": "https://api.whatsapp.com/send?phone=2411576300&text=Hola!%20Me%20interesa%20un%20Estampado%20con%20este%20Dise%C3%B1o%20%22URB-31041%22"
    },
    {
        "sku": "URB-31042",
        "keywords": "urbanos 42",
        "name": "MOD: URB-31042",
        "hot": false,
        "new": false,
        "image": "https://i.ibb.co/Y4Y29gWH/URBANO-42.png",
        "link": "https://api.whatsapp.com/send?phone=2411576300&text=Hola!%20Me%20interesa%20un%20Estampado%20con%20este%20Dise%C3%B1o%20%22URB-31042%22"
    },
    {
        "sku": "URB-31043",
        "keywords": "urbanos 43",
        "name": "MOD: URB-31043",
        "hot": false,
        "new": false,
        "image": "https://i.ibb.co/RRtrgxW/URBANO-43.png",
        "link": "https://api.whatsapp.com/send?phone=2411576300&text=Hola!%20Me%20interesa%20un%20Estampado%20con%20este%20Dise%C3%B1o%20%22URB-31043%22"
    },
    {
        "sku": "URB-31044",
        "keywords": "urbanos 44",
        "name": "MOD: URB-31044",
        "hot": false,
        "new": false,
        "image": "https://i.ibb.co/BV9Z2ZPM/URBANO-44.png",
        "link": "https://api.whatsapp.com/send?phone=2411576300&text=Hola!%20Me%20interesa%20un%20Estampado%20con%20este%20Dise%C3%B1o%20%22URB-31044%22"
    },
    {
        "sku": "URB-31045",
        "keywords": "urbanos 45",
        "name": "MOD: URB-31045",
        "hot": false,
        "new": false,
        "image": "https://i.ibb.co/LDmqPrt2/URBANO-45.png",
        "link": "https://api.whatsapp.com/send?phone=2411576300&text=Hola!%20Me%20interesa%20un%20Estampado%20con%20este%20Dise%C3%B1o%20%22URB-31045%22"
    },
    {
        "sku": "URB-31046",
        "keywords": "urbanos 46",
        "name": "MOD: URB-31046",
        "hot": false,
        "new": false,
        "image": "https://i.ibb.co/hF2KhYLp/URBANO-46.png",
        "link": "https://api.whatsapp.com/send?phone=2411576300&text=Hola!%20Me%20interesa%20un%20Estampado%20con%20este%20Dise%C3%B1o%20%22URB-31046%22"
    },
    {
        "sku": "URB-31047",
        "keywords": "urbanos 47",
        "name": "MOD: URB-31047",
        "hot": false,
        "new": false,
        "image": "https://i.ibb.co/Cps3JF87/URBANO-47.png",
        "link": "https://api.whatsapp.com/send?phone=2411576300&text=Hola!%20Me%20interesa%20un%20Estampado%20con%20este%20Dise%C3%B1o%20%22URB-31047%22"
    },
    {
        "sku": "URB-31048",
        "keywords": "urbanos 48",
        "name": "MOD: URB-31048",
        "hot": false,
        "new": false,
        "image": "https://i.ibb.co/j9JppY4q/URBANO-48.png",
        "link": "https://api.whatsapp.com/send?phone=2411576300&text=Hola!%20Me%20interesa%20un%20Estampado%20con%20este%20Dise%C3%B1o%20%22URB-31048%22"
    },
    {
        "sku": "URB-31049",
        "keywords": "urbanos 49",
        "name": "MOD: URB-31049",
        "hot": false,
        "new": false,
        "image": "https://i.ibb.co/9HZSfT0b/URBANO-49.png",
        "link": "https://api.whatsapp.com/send?phone=2411576300&text=Hola!%20Me%20interesa%20un%20Estampado%20con%20este%20Dise%C3%B1o%20%22URB-31049%22"
    },
    {
        "sku": "URB-31050",
        "keywords": "urbanos 50",
        "name": "MOD: URB-31050",
        "hot": false,
        "new": false,
        "image": "https://i.ibb.co/NnjS8pfn/URBANO-50.png",
        "link": "https://api.whatsapp.com/send?phone=2411576300&text=Hola!%20Me%20interesa%20un%20Estampado%20con%20este%20Dise%C3%B1o%20%22URB-31050%22"
    },
    {
        "sku": "URB-31051",
        "keywords": "urbanos 51",
        "name": "MOD: URB-31051",
        "hot": false,
        "new": false,
        "image": "https://i.ibb.co/FqsgXqYM/URBANO-51.png",
        "link": "https://api.whatsapp.com/send?phone=2411576300&text=Hola!%20Me%20interesa%20un%20Estampado%20con%20este%20Dise%C3%B1o%20%22URB-31051%22"
    },
    {
        "sku": "URB-31052",
        "keywords": "urbanos 52",
        "name": "MOD: URB-31052",
        "hot": false,
        "new": false,
        "image": "https://i.ibb.co/BHZLfRGq/URBANO-52.png",
        "link": "https://api.whatsapp.com/send?phone=2411576300&text=Hola!%20Me%20interesa%20un%20Estampado%20con%20este%20Dise%C3%B1o%20%22URB-31052%22"
    },
    {
        "sku": "URB-31053",
        "keywords": "urbanos 53",
        "name": "MOD: URB-31053",
        "hot": false,
        "new": false,
        "image": "https://i.ibb.co/MkfbBq9K/URBANO-53.png",
        "link": "https://api.whatsapp.com/send?phone=2411576300&text=Hola!%20Me%20interesa%20un%20Estampado%20con%20este%20Dise%C3%B1o%20%22URB-31053%22"
    },
    {
        "sku": "URB-31054",
        "keywords": "urbanos 54",
        "name": "MOD: URB-31054",
        "hot": false,
        "new": false,
        "image": "https://i.ibb.co/S49vCWwt/URBANO-54.png",
        "link": "https://api.whatsapp.com/send?phone=2411576300&text=Hola!%20Me%20interesa%20un%20Estampado%20con%20este%20Dise%C3%B1o%20%22URB-31054%22"
    },
    {
        "sku": "URB-31055",
        "keywords": "urbanos 55",
        "name": "MOD: URB-31055",
        "hot": false,
        "new": false,
        "image": "https://i.ibb.co/w1Qs5Mp/URBANO-55.png",
        "link": "https://api.whatsapp.com/send?phone=2411576300&text=Hola!%20Me%20interesa%20un%20Estampado%20con%20este%20Dise%C3%B1o%20%22URB-31055%22"
    }
]