[
    {
        "sku": "STW-46001",
        "keywords": "streetwear premium 1",
        "name": "MOD: STW-46001",
        "hot": false,
        "new": false,
        "image": "https://i.ibb.co/DPFRQqqn/STREETWEAR-01.png",
        "link": "https://api.whatsapp.com/send?phone=2411576300&text=Hola!%20Me%20interesa%20un%20Estampado%20con%20este%20Dise%C3%B1o%20%22STW-46001%22"
    },
    {
        "sku": "STW-46002",
        "keywords": "streetwear premium 2",
        "name": "MOD: STW-46002",
        "hot": false,
        "new": false,
        "image": "https://i.ibb.co/HDxzwfxv/STREETWEAR-02.png",
        "link": "https://api.whatsapp.com/send?phone=2411576300&text=Hola!%20Me%20interesa%20un%20Estampado%20con%20este%20Dise%C3%B1o%20%22STW-46002%22"
    },
    {
        "sku": "STW-46003",
        "keywords": "streetwear premium 3",
        "name": "MOD: STW-46003",
        "hot": false,
        "new": false,
        "image": "https://i.ibb.co/wZfgV3fp/STREETWEAR-03.png",
        "link": "https://api.whatsapp.com/send?phone=2411576300&text=Hola!%20Me%20interesa%20un%20Estampado%20con%20este%20Dise%C3%B1o%20%22STW-46003%22"
    },
    {
        "sku": "STW-46004",
        "keywords": "streetwear premium 4",
        "name": "MOD: STW-46004",
        "hot": false,
        "new": false,
        "image": "https://i.ibb.co/LD4mZhDF/STREETWEAR-04.png",
        "link": "https://api.whatsapp.com/send?phone=2411576300&text=Hola!%20Me%20interesa%20un%20Estampado%20con%20este%20Dise%C3%B1o%20%22STW-46004%22"
    },
    {
        "sku": "STW-46005",
        "keywords": "streetwear premium 5",
        "name": "MOD: STW-46005",
        "hot": false,
        "new": false,
        "image": "https://i.ibb.co/5X20cB3G/STREETWEAR-05.png",
        "link": "https://api.whatsapp.com/send?phone=2411576300&text=Hola!%20Me%20interesa%20un%20Estampado%20con%20este%20Dise%C3%B1o%20%22STW-46005%22"
    },
    {
        "sku": "STW-46006",
        "keywords": "streetwear premium 6",
        "name": "MOD: STW-46006",
        "hot": false,
        "new": false,
        "image": "https://i.ibb.co/B5wHYSNL/STREETWEAR-06.png",
        "link": "https://api.whatsapp.com/send?phone=2411576300&text=Hola!%20Me%20interesa%20un%20Estampado%20con%20este%20Dise%C3%B1o%20%22STW-46006%22"
    },
    {
        "sku": "STW-46007",
        "keywords": "streetwear premium 7",
        "name": "MOD: STW-46007",
        "hot": false,
        "new": false,
        "image": "https://i.ibb.co/fYPZ6rrz/STREETWEAR-07.png",
        "link": "https://api.whatsapp.com/send?phone=2411576300&text=Hola!%20Me%20interesa%20un%20Estampado%20con%20este%20Dise%C3%B1o%20%22STW-46007%22"
    },
    {
        "sku": "STW-46008",
        "keywords": "streetwear premium 8",
        "name": "MOD: STW-46008",
        "hot": false,
        "new": false,
        "image": "https://i.ibb.co/NPppDPS/STREETWEAR-08.png",
        "link": "https://api.whatsapp.com/send?phone=2411576300&text=Hola!%20Me%20interesa%20un%20Estampado%20con%20este%20Dise%C3%B1o%20%22STW-46008%22"
    },
    {
        "sku": "STW-46009",
        "keywords": "streetwear premium 9",
        "name": "MOD: STW-46009",
        "hot": false,
        "new": false,
        "image": "https://i.ibb.co/PZvp64Gk/STREETWEAR-09.png",
        "link": "https://api.whatsapp.com/send?phone=2411576300&text=Hola!%20Me%20interesa%20un%20Estampado%20con%20este%20Dise%C3%B1o%20%22STW-46009%22"
    },
    {
        "sku": "STW-46010",
        "keywords": "streetwear premium 10",
        "name": "MOD: STW-46010",
        "hot": false,
        "new": false,
        "image": "https://i.ibb.co/99zLc0Fy/STREETWEAR-10.png",
        "link": "https://api.whatsapp.com/send?phone=2411576300&text=Hola!%20Me%20interesa%20un%20Estampado%20con%20este%20Dise%C3%B1o%20%22STW-46010%22"
    },
    {
        "sku": "STW-46011",
        "keywords": "streetwear premium 11",
        "name": "MOD: STW-46011",
        "hot": false,
        "new": false,
        "image": "https://i.ibb.co/mrjhhDf2/STREETWEAR-11.png",
        "link": "https://api.whatsapp.com/send?phone=2411576300&text=Hola!%20Me%20interesa%20un%20Estampado%20con%20este%20Dise%C3%B1o%20%22STW-46011%22"
    },
    {
        "sku": "STW-46012",
        "keywords": "streetwear premium 12",
        "name": "MOD: STW-46012",
        "hot": false,
        "new": false,
        "image": "https://i.ibb.co/SX1ccQSW/STREETWEAR-12.png",
        "link": "https://api.whatsapp.com/send?phone=2411576300&text=Hola!%20Me%20interesa%20un%20Estampado%20con%20este%20Dise%C3%B1o%20%22STW-46012%22"
    },
    {
        "sku": "STW-46013",
        "keywords": "streetwear premium 13",
        "name": "MOD: STW-46013",
        "hot": false,
        "new": false,
        "image": "https://i.ibb.co/q3bqzFTK/STREETWEAR-13.png",
        "link": "https://api.whatsapp.com/send?phone=2411576300&text=Hola!%20Me%20interesa%20un%20Estampado%20con%20este%20Dise%C3%B1o%20%22STW-46013%22"
    },
    {
        "sku": "STW-46014",
        "keywords": "streetwear premium 14",
        "name": "MOD: STW-46014",
        "hot": false,
        "new": false,
        "image": "https://i.ibb.co/qFrddWFY/STREETWEAR-14.png",
        "link": "https://api.whatsapp.com/send?phone=2411576300&text=Hola!%20Me%20interesa%20un%20Estampado%20con%20este%20Dise%C3%B1o%20%22STW-46014%22"
    },
    {
        "sku": "STW-46015",
        "keywords": "streetwear premium 15",
        "name": "MOD: STW-46015",
        "hot": false,
        "new": false,
        "image": "https://i.ibb.co/qFxYT1DG/STREETWEAR-15.png",
        "link": "https://api.whatsapp.com/send?phone=2411576300&text=Hola!%20Me%20interesa%20un%20Estampado%20con%20este%20Dise%C3%B1o%20%22STW-46015%22"
    },
    {
        "sku": "STW-46016",
        "keywords": "streetwear premium 16",
        "name": "MOD: STW-46016",
        "hot": false,
        "new": false,
        "image": "https://i.ibb.co/hFQNgNYz/STREETWEAR-16.png",
        "link": "https://api.whatsapp.com/send?phone=2411576300&text=Hola!%20Me%20interesa%20un%20Estampado%20con%20este%20Dise%C3%B1o%20%22STW-46016%22"
    },
    {
        "sku": "STW-46017",
        "keywords": "streetwear premium 17",
        "name": "MOD: STW-46017",
        "hot": false,
        "new": false,
        "image": "https://i.ibb.co/FkWYcLQC/STREETWEAR-17.png",
        "link": "https://api.whatsapp.com/send?phone=2411576300&text=Hola!%20Me%20interesa%20un%20Estampado%20con%20este%20Dise%C3%B1o%20%22STW-46017%22"
    },
    {
        "sku": "STW-46018",
        "keywords": "streetwear premium 18",
        "name": "MOD: STW-46018",
        "hot": false,
        "new": false,
        "image": "https://i.ibb.co/SDR2nbg4/STREETWEAR-18.png",
        "link": "https://api.whatsapp.com/send?phone=2411576300&text=Hola!%20Me%20interesa%20un%20Estampado%20con%20este%20Dise%C3%B1o%20%22STW-46018%22"
    },
    {
        "sku": "STW-46019",
        "keywords": "streetwear premium 19",
        "name": "MOD: STW-46019",
        "hot": false,
        "new": false,
        "image": "https://i.ibb.co/VcVP7LbD/STREETWEAR-19.png",
        "link": "https://api.whatsapp.com/send?phone=2411576300&text=Hola!%20Me%20interesa%20un%20Estampado%20con%20este%20Dise%C3%B1o%20%22STW-46019%22"
    },
    {
        "sku": "STW-46020",
        "keywords": "streetwear premium 20",
        "name": "MOD: STW-46020",
        "hot": false,
        "new": false,
        "image": "https://i.ibb.co/cKRD3jwV/STREETWEAR-20.png",
        "link": "https://api.whatsapp.com/send?phone=2411576300&text=Hola!%20Me%20interesa%20un%20Estampado%20con%20este%20Dise%C3%B1o%20%22STW-46020%22"
    },
    {
        "sku": "STW-46021",
        "keywords": "streetwear premium 21",
        "name": "MOD: STW-46021",
        "hot": false,
        "new": false,
        "image": "https://i.ibb.co/kVRVXDpj/STREETWEAR-21.png",
        "link": "https://api.whatsapp.com/send?phone=2411576300&text=Hola!%20Me%20interesa%20un%20Estampado%20con%20este%20Dise%C3%B1o%20%22STW-46021%22"
    },
    {
        "sku": "STW-46022",
        "keywords": "streetwear premium 22",
        "name": "MOD: STW-46022",
        "hot": false,
        "new": false,
        "image": "https://i.ibb.co/GfJmyc7r/STREETWEAR-22.png",
        "link": "https://api.whatsapp.com/send?phone=2411576300&text=Hola!%20Me%20interesa%20un%20Estampado%20con%20este%20Dise%C3%B1o%20%22STW-46022%22"
    },
    {
        "sku": "STW-46023",
        "keywords": "streetwear premium 23",
        "name": "MOD: STW-46023",
        "hot": false,
        "new": false,
        "image": "https://i.ibb.co/jkgpKkQX/STREETWEAR-23.png",
        "link": "https://api.whatsapp.com/send?phone=2411576300&text=Hola!%20Me%20interesa%20un%20Estampado%20con%20este%20Dise%C3%B1o%20%22STW-46023%22"
    },
    {
        "sku": "STW-46024",
        "keywords": "streetwear premium 24",
        "name": "MOD: STW-46024",
        "hot": false,
        "new": false,
        "image": "https://i.ibb.co/v4Bp6wt8/STREETWEAR-24.png",
        "link": "https://api.whatsapp.com/send?phone=2411576300&text=Hola!%20Me%20interesa%20un%20Estampado%20con%20este%20Dise%C3%B1o%20%22STW-46024%22"
    },
    {
        "sku": "STW-46025",
        "keywords": "streetwear premium 25",
        "name": "MOD: STW-46025",
        "hot": false,
        "new": false,
        "image": "https://i.ibb.co/zWzb6WSg/STREETWEAR-25.png",
        "link": "https://api.whatsapp.com/send?phone=2411576300&text=Hola!%20Me%20interesa%20un%20Estampado%20con%20este%20Dise%C3%B1o%20%22STW-46025%22"
    },
    {
        "sku": "STW-46026",
        "keywords": "streetwear premium 26",
        "name": "MOD: STW-46026",
        "hot": false,
        "new": false,
        "image": "https://i.ibb.co/gZxm966L/STREETWEAR-26.png",
        "link": "https://api.whatsapp.com/send?phone=2411576300&text=Hola!%20Me%20interesa%20un%20Estampado%20con%20este%20Dise%C3%B1o%20%22STW-46026%22"
    },
    {
        "sku": "STW-46027",
        "keywords": "streetwear premium 27",
        "name": "MOD: STW-46027",
        "hot": false,
        "new": false,
        "image": "https://i.ibb.co/20CSPb0F/STREETWEAR-27.png",
        "link": "https://api.whatsapp.com/send?phone=2411576300&text=Hola!%20Me%20interesa%20un%20Estampado%20con%20este%20Dise%C3%B1o%20%22STW-46027%22"
    },
    {
        "sku": "STW-46028",
        "keywords": "streetwear premium 28",
        "name": "MOD: STW-46028",
        "hot": false,
        "new": false,
        "image": "https://i.ibb.co/gMGTXBQp/STREETWEAR-28.png",
        "link": "https://api.whatsapp.com/send?phone=2411576300&text=Hola!%20Me%20interesa%20un%20Estampado%20con%20este%20Dise%C3%B1o%20%22STW-46028%22"
    },
    {
        "sku": "STW-46029",
        "keywords": "streetwear premium 29",
        "name": "MOD: STW-46029",
        "hot": false,
        "new": false,
        "image": "https://i.ibb.co/s9F5w38R/STREETWEAR-29.png",
        "link": "https://api.whatsapp.com/send?phone=2411576300&text=Hola!%20Me%20interesa%20un%20Estampado%20con%20este%20Dise%C3%B1o%20%22STW-46029%22"
    },
    {
        "sku": "STW-46030",
        "keywords": "streetwear premium 30",
        "name": "MOD: STW-46030",
        "hot": false,
        "new": false,
        "image": "https://i.ibb.co/fgbTFcx/STREETWEAR-30.png",
        "link": "https://api.whatsapp.com/send?phone=2411576300&text=Hola!%20Me%20interesa%20un%20Estampado%20con%20este%20Dise%C3%B1o%20%22STW-46030%22"
    }
]